MANIFEST.in
README.txt
setup.py
turberfield/dynamics/__init__.py
turberfield/dynamics/jobqueue.py
turberfield/dynamics/simulation.py
turberfield/dynamics/types.py
turberfield/dynamics/test/__init__.py
turberfield/dynamics/test/test_simulation.py
turberfield_dynamics.egg-info/PKG-INFO
turberfield_dynamics.egg-info/SOURCES.txt
turberfield_dynamics.egg-info/dependency_links.txt
turberfield_dynamics.egg-info/entry_points.txt
turberfield_dynamics.egg-info/namespace_packages.txt
turberfield_dynamics.egg-info/not-zip-safe
turberfield_dynamics.egg-info/requires.txt
turberfield_dynamics.egg-info/top_level.txt