Metadata-Version: 1.1
Name: turberfield-dynamics
Version: 00.008
Summary: 
Home-page: https://www.assembla.com/spaces/turberfield/messages
Author: D Haynes
Author-email: tundish@thuswise.org
License: UNKNOWN
Platform: UNKNOWN
Classifier: Operating System :: OS Independent
Classifier: Programming Language :: Python :: 3.4
Classifier: License :: OSI Approved :: GNU Affero General Public License v3 or later (AGPLv3+)
